noisi/__init__.py
noisi/main.py
noisi/config/config.yml
noisi/config/config_comments.txt
noisi/config/data_sac_headers.txt
noisi/config/measr_config.yml
noisi/config/measr_config_comments.txt
noisi/config/source_config.yml
noisi/config/source_config_comments.txt
noisi/config/source_setup_parameters.yml
noisi/config/stationlist.csv
noisi/my_classes/__init__.py
noisi/my_classes/noisesource.py
noisi/my_classes/wavefield.py
noisi/scripts/__init__.py
noisi/scripts/adjnt_functs.py
noisi/scripts/correlation.py
noisi/scripts/kernel.py
noisi/scripts/measurements.py
noisi/scripts/rotate_kernel.py
noisi/scripts/run_measurement.py
noisi/scripts/run_sourcesetup.py
noisi/scripts/run_wavefieldprep.py
noisi/scripts/source_grid.py
noisi/util/__init__.py
noisi/util/add_metadata.py
noisi/util/corr_pairs.py
noisi/util/filter.py
noisi/util/geo.py
noisi/util/plot.py
noisi/util/rotate_horizontal_components.py
noisi/util/setup_new.py
noisi/util/smoothing.py
noisi/util/windows.py
noisi-0.1.0a0.dist-info/LICENSE
noisi-0.1.0a0.dist-info/METADATA
noisi-0.1.0a0.dist-info/WHEEL
noisi-0.1.0a0.dist-info/entry_points.txt
noisi-0.1.0a0.dist-info/top_level.txt
noisi-0.1.0a0.dist-info/RECORD
