Metadata-Version: 2.1
Name: noisi
Version: 0.1.0a0
Summary: Package to calculate noise correlations from precomputed seismic wavefields
Home-page: https://github.com/lermert/noisi
Author: L. Ermert, J. Igel, A. Fichtner
Author-email: lermert@fas.harvard.edu, jonas.igel@erdw.ethz.ch
License: GNU Lesser General Public License, Version 3 (LGPLv3) or later
Keywords: Ambient seismic noise
Platform: UNKNOWN
Classifier: Development Status :: 4 - Beta
Classifier: License :: OSI Approved :: GNU Lesser General Public License v3 or later (LGPLv3+)
Classifier: Topic :: Scientific/Engineering
Classifier: Topic :: Scientific/Engineering :: Physics
Classifier: Programming Language :: Python :: 3
Classifier: Operating System :: OS Independent
Classifier: Environment :: Console
Requires-Dist: numpy
Requires-Dist: scipy
Requires-Dist: obspy (>=1.0.1)
Requires-Dist: geographiclib
Requires-Dist: mpi4py (>=2.0.0)
Requires-Dist: pandas
Requires-Dist: h5py
Requires-Dist: PyYaml
Requires-Dist: jupyter
Requires-Dist: pytest
